wordsmith/__init__.py
wordsmith/configuration.py
wordsmith/exceptions.py
wordsmith/narrative.py
wordsmith/project.py
wordsmith/template.py
wordsmith/wordsmith.py
wordsmith-0.5.dist-info/DESCRIPTION.rst
wordsmith-0.5.dist-info/METADATA
wordsmith-0.5.dist-info/RECORD
wordsmith-0.5.dist-info/WHEEL
wordsmith-0.5.dist-info/metadata.json
wordsmith-0.5.dist-info/top_level.txt
